{"x_scores":{"journal_fit":3,"informativeness":3,"clarity":3,"appeal":2},"y_scores":{"journal_fit":5,"informativeness":5,"clarity":5,"appeal":5},"winner":"Y","rationale":"Title Y names both specific ablation modalities, the pediatric population, and the national registry data source, matching JACC's preference for precise, data-anchored titles, while Title X uses vague generic language that obscures the comparison and conveys no data provenance.","loser_weakness":"Title X fails to specify the compared modalities or the data source, making it generic and low-appeal for a JACC readership expecting precision."}