[
  {
    "id": 1645,
    "study_type": "meta_analysis_review",
    "gap_type": "prevalence_or_characterization",
    "opening_move": "premise_then_however",
    "contribution_frame": "feasibility_safety_demo",
    "results_logic": "descriptive_only",
    "benchmarking": "none",
    "conclusion_stance": "practical_modest",
    "certainty_calibration": "matches_design",
    "voice": "impersonal",
    "external_validation": "not_applicable",
    "fits_codebook": true,
    "novel_pattern": "",
    "evidence_quote": "limited data in the current literature regarding LAAO IE underscores the need"
  },
  {
    "id": 1646,
    "study_type": "original_clinical",
    "gap_type": "comparative_unknown",
    "opening_move": "entity_definition",
    "contribution_frame": "procedural_refinement",
    "results_logic": "p_value_only",
    "benchmarking": "vs_alternative_technique",
    "conclusion_stance": "decisive_clinical",
    "certainty_calibration": "matches_design",
    "voice": "impersonal",
    "external_validation": "internal_only",
    "fits_codebook": true,
    "novel_pattern": "",
    "evidence_quote": "OT mapping leads to significantly different substrate display, map density, voltage"
  },
  {
    "id": 1647,
    "study_type": "original_clinical",
    "gap_type": "mechanistic_deficit",
    "opening_move": "premise_then_however",
    "contribution_frame": "mechanism_insight",
    "results_logic": "descriptive_only",
    "benchmarking": "none",
    "conclusion_stance": "mechanistic_elevation",
    "certainty_calibration": "matches_design",
    "voice": "impersonal",
    "external_validation": "internal_only",
    "fits_codebook": true,
    "novel_pattern": "",
    "evidence_quote": "main mechanism of human PMVT maintenance was rotational activity over ventricular apex"
  },
  {
    "id": 1648,
    "study_type": "meta_analysis_review",
    "gap_type": "comparative_unknown",
    "opening_move": "premise_then_however",
    "contribution_frame": "evidence_synthesis_meta",
    "results_logic": "meta_pooled_effect",
    "benchmarking": "vs_alternative_technique",
    "conclusion_stance": "translational_honest",
    "certainty_calibration": "matches_design",
    "voice": "impersonal",
    "external_validation": "not_applicable",
    "fits_codebook": true,
    "novel_pattern": "",
    "evidence_quote": "PFA appears to be associated with a slightly higher risk of AKI than RFA"
  },
  {
    "id": 1649,
    "study_type": "original_clinical",
    "gap_type": "comparative_unknown",
    "opening_move": "premise_then_however",
    "contribution_frame": "comparative_effectiveness",
    "results_logic": "descriptive_only",
    "benchmarking": "vs_alternative_technique",
    "conclusion_stance": "decisive_clinical",
    "certainty_calibration": "matches_design",
    "voice": "impersonal",
    "external_validation": "internal_only",
    "fits_codebook": true,
    "novel_pattern": "",
    "evidence_quote": "initial strategy with Watchman FLX in patients with favorable LAA anatomy would reduce risk"
  },
  {
    "id": 1650,
    "study_type": "original_clinical",
    "gap_type": "feasibility_in_niche",
    "opening_move": "aim_first",
    "contribution_frame": "feasibility_safety_demo",
    "results_logic": "descriptive_only",
    "benchmarking": "none",
    "conclusion_stance": "practical_modest",
    "certainty_calibration": "matches_design",
    "voice": "impersonal",
    "external_validation": "internal_only",
    "fits_codebook": true,
    "novel_pattern": "",
    "evidence_quote": "IM two-incision technique allows optimal positioning achieving low PRAETORIAN score with high conversion rate"
  },
  {
    "id": 1651,
    "study_type": "meta_analysis_review",
    "gap_type": "optimization_unknown",
    "opening_move": "clinical_problem_first",
    "contribution_frame": "evidence_synthesis_meta",
    "results_logic": "descriptive_only",
    "benchmarking": "none",
    "conclusion_stance": "translational_honest",
    "certainty_calibration": "matches_design",
    "voice": "impersonal",
    "external_validation": "not_applicable",
    "fits_codebook": true,
    "novel_pattern": "",
    "evidence_quote": "combined endocardial-epicardial approaches, reduces VT burden but faces high recurrence rates"
  },
  {
    "id": 1652,
    "study_type": "original_clinical",
    "gap_type": "prevalence_or_characterization",
    "opening_move": "premise_then_however",
    "contribution_frame": "realworld_scale_evidence",
    "results_logic": "p_value_only",
    "benchmarking": "vs_baseline_prepost",
    "conclusion_stance": "decisive_clinical",
    "certainty_calibration": "matches_design",
    "voice": "first_person_we",
    "external_validation": "internal_only",
    "fits_codebook": true,
    "novel_pattern": "",
    "evidence_quote": "HCM group had significantly higher 90-day rates of persistent LA thrombus"
  },
  {
    "id": 1653,
    "study_type": "original_clinical",
    "gap_type": "feasibility_in_niche",
    "opening_move": "clinical_problem_first",
    "contribution_frame": "feasibility_safety_demo",
    "results_logic": "descriptive_only",
    "benchmarking": "vs_alternative_technique",
    "conclusion_stance": "practical_modest",
    "certainty_calibration": "matches_design",
    "voice": "impersonal",
    "external_validation": "internal_only",
    "fits_codebook": true,
    "novel_pattern": "",
    "evidence_quote": "ablation of mid- or epicardial VT circuits from CVS branches are feasible and safe"
  },
  {
    "id": 1654,
    "study_type": "original_clinical",
    "gap_type": "feasibility_in_niche",
    "opening_move": "entity_definition",
    "contribution_frame": "feasibility_safety_demo",
    "results_logic": "descriptive_only",
    "benchmarking": "none",
    "conclusion_stance": "practical_modest",
    "certainty_calibration": "matches_design",
    "voice": "impersonal",
    "external_validation": "internal_only",
    "fits_codebook": true,
    "novel_pattern": "",
    "evidence_quote": "LUX-Dx implantation appears efficient and straightforward, with favorable post-implantation sensing values"
  },
  {
    "id": 1655,
    "study_type": "original_clinical",
    "gap_type": "prevalence_or_characterization",
    "opening_move": "clinical_problem_first",
    "contribution_frame": "realworld_scale_evidence",
    "results_logic": "p_value_only",
    "benchmarking": "vs_baseline_prepost",
    "conclusion_stance": "translational_honest",
    "certainty_calibration": "matches_design",
    "voice": "first_person_we",
    "external_validation": "internal_only",
    "fits_codebook": true,
    "novel_pattern": "",
    "evidence_quote": "utilization of MCS during VT ablation was associated with significantly worse inpatient outcomes"
  },
  {
    "id": 1656,
    "study_type": "original_clinical",
    "gap_type": "optimization_unknown",
    "opening_move": "premise_then_however",
    "contribution_frame": "prognostic_predictor",
    "results_logic": "p_value_only",
    "benchmarking": "none",
    "conclusion_stance": "decisive_clinical",
    "certainty_calibration": "matches_design",
    "voice": "first_person_we",
    "external_validation": "internal_only",
    "fits_codebook": true,
    "novel_pattern": "",
    "evidence_quote": "patients with lower heart rate increase are prone to recurrence while those with higher increase"
  }
]
