[
  {
    "id": 1405,
    "study_type": "original_clinical",
    "gap_type": "feasibility_in_niche",
    "opening_move": "premise_then_however",
    "contribution_frame": "feasibility_safety_demo",
    "results_logic": "descriptive_only",
    "benchmarking": "none",
    "conclusion_stance": "practical_modest",
    "certainty_calibration": "matches_design",
    "voice": "impersonal",
    "external_validation": "not_applicable",
    "fits_codebook": true,
    "novel_pattern": "",
    "evidence_quote": "CMR aided ablation is feasible and effective in patients with scar related VT"
  },
  {
    "id": 1406,
    "study_type": "original_clinical",
    "gap_type": "comparative_unknown",
    "opening_move": "premise_then_however",
    "contribution_frame": "comparative_effectiveness",
    "results_logic": "noninferiority",
    "benchmarking": "vs_alternative_technique",
    "conclusion_stance": "decisive_clinical",
    "certainty_calibration": "matches_design",
    "voice": "impersonal",
    "external_validation": "not_applicable",
    "fits_codebook": true,
    "novel_pattern": "",
    "evidence_quote": "single-catheter approach is not inferior to the conventional multiple-catheter approach"
  },
  {
    "id": 1407,
    "study_type": "original_clinical",
    "gap_type": "feasibility_in_niche",
    "opening_move": "premise_then_however",
    "contribution_frame": "feasibility_safety_demo",
    "results_logic": "p_value_only",
    "benchmarking": "vs_baseline_prepost",
    "conclusion_stance": "translational_honest",
    "certainty_calibration": "matches_design",
    "voice": "impersonal",
    "external_validation": "not_applicable",
    "fits_codebook": true,
    "novel_pattern": "",
    "evidence_quote": "demonstrates the safety and feasibility of epicardial ablation of the GP using PF"
  },
  {
    "id": 1408,
    "study_type": "original_clinical",
    "gap_type": "feasibility_in_niche",
    "opening_move": "premise_then_however",
    "contribution_frame": "feasibility_safety_demo",
    "results_logic": "descriptive_only",
    "benchmarking": "vs_alternative_technique",
    "conclusion_stance": "practical_modest",
    "certainty_calibration": "matches_design",
    "voice": "impersonal",
    "external_validation": "not_applicable",
    "fits_codebook": true,
    "novel_pattern": "",
    "evidence_quote": "fluoroless GP ablation can be performed safely"
  },
  {
    "id": 1409,
    "study_type": "original_clinical",
    "gap_type": "feasibility_in_niche",
    "opening_move": "premise_then_however",
    "contribution_frame": "feasibility_safety_demo",
    "results_logic": "descriptive_only",
    "benchmarking": "none",
    "conclusion_stance": "practical_modest",
    "certainty_calibration": "matches_design",
    "voice": "impersonal",
    "external_validation": "not_applicable",
    "fits_codebook": true,
    "novel_pattern": "",
    "evidence_quote": "no reinfections occurred in over 2.5 years follow-up; LP is an appealing replacement device"
  },
  {
    "id": 1410,
    "study_type": "original_clinical",
    "gap_type": "comparative_unknown",
    "opening_move": "trial_or_cohort_name_first",
    "contribution_frame": "comparative_effectiveness",
    "results_logic": "effectsize_comparator_ci",
    "benchmarking": "vs_alternative_technique",
    "conclusion_stance": "decisive_clinical",
    "certainty_calibration": "matches_design",
    "voice": "impersonal",
    "external_validation": "not_applicable",
    "fits_codebook": true,
    "novel_pattern": "",
    "evidence_quote": "similar efficacy to radiofrequency CTI ablation but significantly reduces occurrence of subsequent AF"
  },
  {
    "id": 1411,
    "study_type": "original_clinical",
    "gap_type": "capability_gap",
    "opening_move": "aim_first",
    "contribution_frame": "procedural_refinement",
    "results_logic": "descriptive_only",
    "benchmarking": "vs_alternative_technique",
    "conclusion_stance": "practical_modest",
    "certainty_calibration": "matches_design",
    "voice": "impersonal",
    "external_validation": "not_applicable",
    "fits_codebook": true,
    "novel_pattern": "",
    "evidence_quote": "catheter is less suited for ablation of the mitral isthmus and the anterior line"
  },
  {
    "id": 1412,
    "study_type": "original_clinical",
    "gap_type": "comparative_unknown",
    "opening_move": "premise_then_however",
    "contribution_frame": "comparative_effectiveness",
    "results_logic": "effectsize_comparator_ci",
    "benchmarking": "vs_alternative_technique",
    "conclusion_stance": "decisive_clinical",
    "certainty_calibration": "matches_design",
    "voice": "impersonal",
    "external_validation": "not_applicable",
    "fits_codebook": true,
    "novel_pattern": "",
    "evidence_quote": "LBBAP was associated with reduced adverse clinical outcome compared to accurate RVSP"
  },
  {
    "id": 1413,
    "study_type": "meta_analysis_review",
    "gap_type": "prevalence_or_characterization",
    "opening_move": "clinical_problem_first",
    "contribution_frame": "evidence_synthesis_meta",
    "results_logic": "descriptive_only",
    "benchmarking": "none",
    "conclusion_stance": "exploratory_hypothesis_generating",
    "certainty_calibration": "matches_design",
    "voice": "impersonal",
    "external_validation": "not_applicable",
    "fits_codebook": true,
    "novel_pattern": "",
    "evidence_quote": "additional research is required to assess suitable candidates, timing, and strategies for PDL"
  },
  {
    "id": 1414,
    "study_type": "original_clinical",
    "gap_type": "prevalence_or_characterization",
    "opening_move": "premise_then_however",
    "contribution_frame": "realworld_scale_evidence",
    "results_logic": "descriptive_only",
    "benchmarking": "none",
    "conclusion_stance": "practical_modest",
    "certainty_calibration": "matches_design",
    "voice": "impersonal",
    "external_validation": "not_applicable",
    "fits_codebook": true,
    "novel_pattern": "",
    "evidence_quote": "regional variations in patient selection and procedural characteristics have not been well characterized"
  },
  {
    "id": 1415,
    "study_type": "original_clinical",
    "gap_type": "prevalence_or_characterization",
    "opening_move": "premise_then_however",
    "contribution_frame": "prognostic_predictor",
    "results_logic": "effectsize_comparator_ci",
    "benchmarking": "none",
    "conclusion_stance": "exploratory_hypothesis_generating",
    "certainty_calibration": "matches_design",
    "voice": "impersonal",
    "external_validation": "not_applicable",
    "fits_codebook": true,
    "novel_pattern": "",
    "evidence_quote": "prognosis of mixed cardiomyopathy in patients with ICDs has not been investigated"
  },
  {
    "id": 1416,
    "study_type": "meta_analysis_review",
    "gap_type": "capability_gap",
    "opening_move": "premise_then_however",
    "contribution_frame": "evidence_synthesis_meta",
    "results_logic": "descriptive_only",
    "benchmarking": "none",
    "conclusion_stance": "practical_modest",
    "certainty_calibration": "matches_design",
    "voice": "impersonal",
    "external_validation": "not_applicable",
    "fits_codebook": true,
    "novel_pattern": "",
    "evidence_quote": "innovations in VA ablation have great potential to improve procedural safety and procedural success"
  }
]
