[
  {
    "id": 397,
    "study_type": "original_clinical",
    "gap_type": "comparative_unknown",
    "opening_move": "premise_then_however",
    "contribution_frame": "comparative_effectiveness",
    "results_logic": "effectsize_comparator_ci",
    "benchmarking": "vs_alternative_technique",
    "conclusion_stance": "null_finding_neutral",
    "certainty_calibration": "matches_design",
    "voice": "impersonal",
    "external_validation": "not_applicable",
    "fits_codebook": true,
    "novel_pattern": "",
    "evidence_quote": "addition of mapping-guided ablation to PVI did not improve clinical outcomes"
  },
  {
    "id": 398,
    "study_type": "meta_analysis_review",
    "gap_type": "mechanistic_deficit",
    "opening_move": "premise_then_however",
    "contribution_frame": "mechanism_insight",
    "results_logic": "descriptive_only",
    "benchmarking": "none",
    "conclusion_stance": "exploratory_hypothesis_generating",
    "certainty_calibration": "matches_design",
    "voice": "impersonal",
    "external_validation": "not_applicable",
    "fits_codebook": true,
    "novel_pattern": "",
    "evidence_quote": "no current strategy that improves AF outcomes beyond pulmonary vein isolation in all patients"
  },
  {
    "id": 399,
    "study_type": "original_clinical",
    "gap_type": "comparative_unknown",
    "opening_move": "trial_or_cohort_name_first",
    "contribution_frame": "feasibility_safety_demo",
    "results_logic": "effectsize_comparator_ci",
    "benchmarking": "vs_baseline_prepost",
    "conclusion_stance": "exploratory_hypothesis_generating",
    "certainty_calibration": "matches_design",
    "voice": "impersonal",
    "external_validation": "not_applicable",
    "fits_codebook": true,
    "novel_pattern": "",
    "evidence_quote": "potential impact of atrial fibrillation screening on HF remains unknown"
  },
  {
    "id": 400,
    "study_type": "original_clinical",
    "gap_type": "feasibility_in_niche",
    "opening_move": "clinical_problem_first",
    "contribution_frame": "procedural_refinement",
    "results_logic": "effectsize_comparator_ci",
    "benchmarking": "vs_alternative_technique",
    "conclusion_stance": "decisive_clinical",
    "certainty_calibration": "matches_design",
    "voice": "impersonal",
    "external_validation": "not_applicable",
    "fits_codebook": true,
    "novel_pattern": "",
    "evidence_quote": "PPoP reduces obstruction and improves exercise performance in severely symptomatic patients"
  },
  {
    "id": 401,
    "study_type": "original_preclinical_basic",
    "gap_type": "mechanistic_deficit",
    "opening_move": "premise_then_however",
    "contribution_frame": "mechanism_insight",
    "results_logic": "descriptive_only",
    "benchmarking": "none",
    "conclusion_stance": "mechanistic_elevation",
    "certainty_calibration": "matches_design",
    "voice": "impersonal",
    "external_validation": "not_applicable",
    "fits_codebook": true,
    "novel_pattern": "",
    "evidence_quote": "whether Sirts involved in age-related AF and its underlying mechanisms remain unknown"
  },
  {
    "id": 402,
    "study_type": "original_preclinical_basic",
    "gap_type": "mechanistic_deficit",
    "opening_move": "premise_then_however",
    "contribution_frame": "mechanism_insight",
    "results_logic": "discriminator_threshold_roc",
    "benchmarking": "vs_existing_model",
    "conclusion_stance": "mechanistic_elevation",
    "certainty_calibration": "matches_design",
    "voice": "impersonal",
    "external_validation": "external",
    "fits_codebook": false,
    "novel_pattern": "physics/power-law framework applied to fibrillation duration; mixed computational+clinical validation; no therapeutic claim",
    "evidence_quote": "quantitative framework to explain episode durations remains elusive"
  },
  {
    "id": 403,
    "study_type": "original_clinical",
    "gap_type": "prevalence_or_characterization",
    "opening_move": "premise_then_however",
    "contribution_frame": "realworld_scale_evidence",
    "results_logic": "effectsize_comparator_ci",
    "benchmarking": "vs_baseline_prepost",
    "conclusion_stance": "practical_modest",
    "certainty_calibration": "matches_design",
    "voice": "impersonal",
    "external_validation": "not_applicable",
    "fits_codebook": true,
    "novel_pattern": "",
    "evidence_quote": "temporal differences in AF burden associated with HF hospitalization risk"
  },
  {
    "id": 404,
    "study_type": "original_clinical",
    "gap_type": "comparative_unknown",
    "opening_move": "premise_then_however",
    "contribution_frame": "comparative_effectiveness",
    "results_logic": "effectsize_comparator_ci",
    "benchmarking": "vs_baseline_prepost",
    "conclusion_stance": "practical_modest",
    "certainty_calibration": "matches_design",
    "voice": "impersonal",
    "external_validation": "not_applicable",
    "fits_codebook": true,
    "novel_pattern": "",
    "evidence_quote": "outcomes of atrial fibrillation seem to be variable between males and females"
  },
  {
    "id": 405,
    "study_type": "original_clinical",
    "gap_type": "feasibility_in_niche",
    "opening_move": "clinical_problem_first",
    "contribution_frame": "procedural_refinement",
    "results_logic": "effectsize_comparator_ci",
    "benchmarking": "vs_guideline_standard",
    "conclusion_stance": "decisive_clinical",
    "certainty_calibration": "matches_design",
    "voice": "impersonal",
    "external_validation": "not_applicable",
    "fits_codebook": true,
    "novel_pattern": "",
    "evidence_quote": "epicardial approach is still regarded as a second-step strategy, due to the risk of complications"
  },
  {
    "id": 406,
    "study_type": "original_clinical",
    "gap_type": "capability_gap",
    "opening_move": "hypothesis_first",
    "contribution_frame": "procedural_refinement",
    "results_logic": "p_value_only",
    "benchmarking": "vs_alternative_technique",
    "conclusion_stance": "practical_modest",
    "certainty_calibration": "matches_design",
    "voice": "first_person_we",
    "external_validation": "not_applicable",
    "fits_codebook": true,
    "novel_pattern": "",
    "evidence_quote": "pops would be preceded by intracardiac echocardiography findings as well as a large impedance fall"
  },
  {
    "id": 407,
    "study_type": "original_preclinical_basic",
    "gap_type": "feasibility_in_niche",
    "opening_move": "premise_then_however",
    "contribution_frame": "feasibility_safety_demo",
    "results_logic": "descriptive_only",
    "benchmarking": "vs_alternative_technique",
    "conclusion_stance": "translational_honest",
    "certainty_calibration": "matches_design",
    "voice": "impersonal",
    "external_validation": "not_applicable",
    "fits_codebook": true,
    "novel_pattern": "",
    "evidence_quote": "nanosecond pulses are thought to primarily electroporate intracellular organelles"
  },
  {
    "id": 408,
    "study_type": "original_preclinical_basic",
    "gap_type": "capability_gap",
    "opening_move": "premise_then_however",
    "contribution_frame": "feasibility_safety_demo",
    "results_logic": "descriptive_only",
    "benchmarking": "vs_alternative_technique",
    "conclusion_stance": "translational_honest",
    "certainty_calibration": "matches_design",
    "voice": "impersonal",
    "external_validation": "not_applicable",
    "fits_codebook": true,
    "novel_pattern": "",
    "evidence_quote": "little is known about PFA's ability to target intracavitary structures, epicardium"
  }
]
