[
  {
    "id": 1621,
    "study_type": "original_clinical",
    "gap_type": "comparative_unknown",
    "opening_move": "premise_then_however",
    "contribution_frame": "procedural_refinement",
    "results_logic": "discriminator_threshold_roc",
    "benchmarking": "vs_alternative_technique",
    "conclusion_stance": "decisive_clinical",
    "certainty_calibration": "matches_design",
    "voice": "first_person_we",
    "external_validation": "internal_only",
    "fits_codebook": true,
    "novel_pattern": "",
    "evidence_quote": "differential diagnosis between AVRT and atypical AVNRT is sometimes challenging"
  },
  {
    "id": 1622,
    "study_type": "original_clinical",
    "gap_type": "capability_gap",
    "opening_move": "premise_then_however",
    "contribution_frame": "procedural_refinement",
    "results_logic": "p_value_only",
    "benchmarking": "vs_alternative_technique",
    "conclusion_stance": "practical_modest",
    "certainty_calibration": "matches_design",
    "voice": "impersonal",
    "external_validation": "internal_only",
    "fits_codebook": true,
    "novel_pattern": "",
    "evidence_quote": "validation of PV isolation using only the Achieve catheter following cryoballoon ablation is imperfect"
  },
  {
    "id": 1623,
    "study_type": "original_clinical",
    "gap_type": "comparative_unknown",
    "opening_move": "premise_then_however",
    "contribution_frame": "realworld_scale_evidence",
    "results_logic": "effectsize_comparator_ci",
    "benchmarking": "vs_alternative_technique",
    "conclusion_stance": "practical_modest",
    "certainty_calibration": "matches_design",
    "voice": "impersonal",
    "external_validation": "internal_only",
    "fits_codebook": true,
    "novel_pattern": "",
    "evidence_quote": "impact of infective vs sterile indications of TLR on mortality and major adverse events"
  },
  {
    "id": 1624,
    "study_type": "case_report_series",
    "gap_type": "literature_void_weak",
    "opening_move": "premise_then_however",
    "contribution_frame": "feasibility_safety_demo",
    "results_logic": "descriptive_only",
    "benchmarking": "none",
    "conclusion_stance": "exploratory_hypothesis_generating",
    "certainty_calibration": "matches_design",
    "voice": "impersonal",
    "external_validation": "not_applicable",
    "fits_codebook": true,
    "novel_pattern": "",
    "evidence_quote": "rare variations that have not been previously reported exist"
  },
  {
    "id": 1625,
    "study_type": "original_clinical",
    "gap_type": "capability_gap",
    "opening_move": "premise_then_however",
    "contribution_frame": "procedural_refinement",
    "results_logic": "effectsize_comparator_ci",
    "benchmarking": "vs_alternative_technique",
    "conclusion_stance": "practical_modest",
    "certainty_calibration": "matches_design",
    "voice": "impersonal",
    "external_validation": "internal_only",
    "fits_codebook": true,
    "novel_pattern": "",
    "evidence_quote": "clinical attempts to selectively ablate near pulmonary vein myocardial sleeves demonstrated a higher recurrence rate"
  },
  {
    "id": 1626,
    "study_type": "original_clinical",
    "gap_type": "optimization_unknown",
    "opening_move": "premise_then_however",
    "contribution_frame": "feasibility_safety_demo",
    "results_logic": "p_value_only",
    "benchmarking": "vs_alternative_technique",
    "conclusion_stance": "practical_modest",
    "certainty_calibration": "matches_design",
    "voice": "impersonal",
    "external_validation": "internal_only",
    "fits_codebook": true,
    "novel_pattern": "",
    "evidence_quote": "pressure waveform-based PV occlusion assessment is feasible and safe and significantly reduces contrast medium"
  },
  {
    "id": 1627,
    "study_type": "original_clinical",
    "gap_type": "mechanistic_deficit",
    "opening_move": "premise_then_however",
    "contribution_frame": "procedural_refinement",
    "results_logic": "descriptive_only",
    "benchmarking": "vs_guideline_standard",
    "conclusion_stance": "mechanistic_elevation",
    "certainty_calibration": "matches_design",
    "voice": "impersonal",
    "external_validation": "internal_only",
    "fits_codebook": true,
    "novel_pattern": "",
    "evidence_quote": "low voltage areas in the right atrium may yield misleading mapping results"
  },
  {
    "id": 1628,
    "study_type": "original_clinical",
    "gap_type": "prevalence_or_characterization",
    "opening_move": "premise_then_however",
    "contribution_frame": "comparative_effectiveness",
    "results_logic": "p_value_only",
    "benchmarking": "vs_alternative_technique",
    "conclusion_stance": "decisive_clinical",
    "certainty_calibration": "matches_design",
    "voice": "first_person_we",
    "external_validation": "internal_only",
    "fits_codebook": true,
    "novel_pattern": "",
    "evidence_quote": "limited studies have shown association between treatment-limiting arrhythmias and TKI, particularly ibrutinib"
  },
  {
    "id": 1629,
    "study_type": "original_clinical",
    "gap_type": "capability_gap",
    "opening_move": "premise_then_however",
    "contribution_frame": "procedural_refinement",
    "results_logic": "p_value_only",
    "benchmarking": "vs_alternative_technique",
    "conclusion_stance": "practical_modest",
    "certainty_calibration": "matches_design",
    "voice": "impersonal",
    "external_validation": "internal_only",
    "fits_codebook": true,
    "novel_pattern": "",
    "evidence_quote": "PF analysis provides a robust and reproducible method for identifying arrhythmogenic substrates in VT ablation"
  },
  {
    "id": 1630,
    "study_type": "original_clinical",
    "gap_type": "optimization_unknown",
    "opening_move": "premise_then_however",
    "contribution_frame": "procedural_refinement",
    "results_logic": "p_value_only",
    "benchmarking": "vs_alternative_technique",
    "conclusion_stance": "decisive_clinical",
    "certainty_calibration": "matches_design",
    "voice": "impersonal",
    "external_validation": "internal_only",
    "fits_codebook": true,
    "novel_pattern": "",
    "evidence_quote": "mitral isthmus ablation is technically difficult, and incomplete block line is not uncommon"
  },
  {
    "id": 1631,
    "study_type": "original_clinical",
    "gap_type": "comparative_unknown",
    "opening_move": "premise_then_however",
    "contribution_frame": "feasibility_safety_demo",
    "results_logic": "descriptive_only",
    "benchmarking": "none",
    "conclusion_stance": "mechanistic_elevation",
    "certainty_calibration": "matches_design",
    "voice": "impersonal",
    "external_validation": "internal_only",
    "fits_codebook": true,
    "novel_pattern": "",
    "evidence_quote": "few prospective studies have analyzed lead localization using imaging techniques"
  },
  {
    "id": 1632,
    "study_type": "original_preclinical_basic",
    "gap_type": "capability_gap",
    "opening_move": "premise_then_however",
    "contribution_frame": "procedural_refinement",
    "results_logic": "descriptive_only",
    "benchmarking": "none",
    "conclusion_stance": "practical_modest",
    "certainty_calibration": "matches_design",
    "voice": "first_person_we",
    "external_validation": "internal_only",
    "fits_codebook": true,
    "novel_pattern": "",
    "evidence_quote": "spatial differences in conduction velocity are critical for cardiac arrhythmias induction"
  }
]
